{
  "en": [
    {
      "question": "hello",
      "answer": "Hello! How can I help you today?"
    },
    {
      "question": "how are you",
      "answer": "I'm doing great! Thanks for asking. How can I assist you?"
    },
    {
      "question": "what is your name",
      "answer": "I'm a multilingual chatbot powered by AI. You can call me ChatBot!"
    },
    {
      "question": "help",
      "answer": "I can help you with general questions. If I'm online, I'll use AI to give you better answers!"
    },
    {
      "question": "bye",
      "answer": "Goodbye! Have a great day!"
    }
  ],
  "es": [
    {
      "question": "hola",
      "answer": "¡Hola! ¿Cómo puedo ayudarte hoy?"
    },
    {
      "question": "cómo estás",
      "answer": "¡Estoy muy bien! Gracias por preguntar. ¿Cómo puedo ayudarte?"
    }
  ],
  "fr": [
    {
      "question": "bonjour",
      "answer": "Bonjour! Comment puis-je vous aider aujourd'hui?"
    }
  ],
  "de": [
    {
      "question": "hallo",
      "answer": "Hallo! Wie kann ich Ihnen heute helfen?"
    }
  ],
  "zh": [
    {
      "question": "你好",
      "answer": "你好！我今天能帮你什么？"
    }
  ],
  "ja": [
    {
      "question": "こんにちは",
      "answer": "こんにちは！どのようにお手伝いできますか？"
    }
  ],
  "hi": [
    {
      "question": "नमस्ते",
      "answer": "नमस्ते! आज मैं आपकी कैसे मदद कर सकता हूँ?"
    },
    {
      "question": "आप कैसे हैं",
      "answer": "मैं बहुत अच्छा हूँ! पूछने के लिए धन्यवाद। मैं आपकी कैसे सहायता कर सकता हूँ?"
    }
  ],
  "ta": [
    {
      "question": "வணக்கம்",
      "answer": "வணக்கம்! இன்று நான் உங்களுக்கு எவ்வாறு உதவ முடியும்?"
    },
    {
      "question": "நீங்கள் எப்படி இருக்கிறீர்கள்",
      "answer": "நான் நன்றாக இருக்கிறேன்! கேட்டதற்கு நன்றி. நான் உங்களுக்கு எவ்வாறு உதவ முடியும்?"
    },
    {
      "question": "உங்கள் பெயர் என்ன",
      "answer": "நான் AI ஆல் இயக்கப்படும் பல்மொழி அரட்டைப் பொறி. நீங்கள் என்னை ChatBot என்று அழைக்கலாம்!"
    },
    {
      "question": "உதவி",
      "answer": "நான் பொதுவான கேள்விகளுக்கு உதவ முடியும். நான் ஆன்லைனில் இருந்தால், சிறந்த பதில்களைத் தர AI ஐப் பயன்படுத்துவேன்!"
    },
    {
      "question": "பிரியாவிடை",
      "answer": "பிரியாவிடை! உங்கள் நாள் நன்றாக அமையட்டும்!"
    },
    {
      "question": "நன்றி",
      "answer": "மிக்க நன்றி! உங்களுக்கு உதவ முடிந்ததில் மகிழ்ச்சி!"
    }
  ]
}